xxlGsc/__init__.py
xxlGsc/xxlGsc.py
xxlGsc-0.1.dist-info/LICENSE
xxlGsc-0.1.dist-info/METADATA
xxlGsc-0.1.dist-info/WHEEL
xxlGsc-0.1.dist-info/top_level.txt
xxlGsc-0.1.dist-info/RECORD
